hypertable
flask_hypertable
hyperthrift
