Metadata-Version: 1.1
Name: Flask-Hypertable
Version: 0.3.0
Summary: A Flask extension for Hypertable over Thrift.
Home-page: https://github.com/coderfi/Flask-Hypertable
Author: Fairiz Azizi
Author-email: coderfi@gmail.com
License: BSD
Keywords: Flask Hypertable
Platform: UNKNOWN
Classifier: Development Status :: 2 - Pre-Alpha
Classifier: Intended Audience :: Developers
Classifier: License :: OSI Approved :: BSD License
Classifier: Natural Language :: English
Classifier: Programming Language :: Python :: 2
Classifier: Programming Language :: Python :: 2.6
Classifier: Programming Language :: Python :: 2.7
